{
  "etiqueta_original": "derecha",
  "frases": [
    {
      "frase": "En el mundo, en la Argentina y en el mundo.",
      "entidades_detectadas": [
        "argentina"
      ]
    },
    {
      "frase": "¿Dónde estaban cuando Alberto Fernández, siendo presidente de la Nación, golpeó y encerró a su mujer en la Quinta de Olivos?",
      "entidades_detectadas": [
        "alberto",
        "presidente"
      ]
    },
    {
      "frase": "¿Dónde estaban cuando el amigo Maduro se llevó secuestrado al gendarme argentino Nahuel Agustín Gacio?",
      "entidades_detectadas": [
        "maduro"
      ]
    },
    {
      "frase": "Cristina Fernández de Kirchner, 66% de imagen negativa.",
      "entidades_detectadas": [
        "cristina",
        "fernández"
      ]
    },
    {
      "frase": "Sergio Massa, 67% de imagen negativa.",
      "entidades_detectadas": [
        "sergio"
      ]
    },
    {
      "frase": "A ver, después te queda Alberto Fernández.",
      "entidades_detectadas": [
        "alberto"
      ]
    },
    {
      "frase": "Después tienes al matrimonio Massa - Galmarini.",
      "entidades_detectadas": [
        "massa"
      ]
    },
    {
      "frase": "Y después tenemos a la izquierda, para cerrar, más conocida como Movimiento 2.5, con gente divina como Tati Almeida, que dice que \"la basura\" de Milei va a terminar en el tacho de la historia.",
      "entidades_detectadas": [
        "milei"
      ]
    },
    {
      "frase": "Yo creo que Milei se levanta todos los días y agradece tener esta oposición.",
      "entidades_detectadas": [
        "milei"
      ]
    },
    {
      "frase": "Son, antes el PJ era un partido poderoso, hegemónico, el partido de los laburantes, de los trabajadores, de los obreros; hoy son un partido chiquito, el partido de las minorías.",
      "entidades_detectadas": [
        "pj"
      ]
    }
  ]
}