{
  "etiqueta_original": "derecha",
  "frases": [
    {
      "frase": "Es muy probable que vengan por la cabeza de algunos periodistas que estamos en contra de los K y que hemos estado sistemáticamente, que seguiremos estando, no del peronismo, si es lo K.",
      "entidades_detectadas": [
        "estado"
      ]
    },
    {
      "frase": "En Venezuela se les fue de las manos, en Cuba se les fue de las manos, pero que no se nos vaya de las manos de la Argentina.",
      "entidades_detectadas": [
        "venezuela",
        "cuba"
      ]
    }
  ]
}