{
  "etiqueta_original": "izquierda",
  "frases": [
    {
      "frase": "Walter Santiago, más conocido como Alfa, sorprendió con su presencia en el acto libertario de Mar del Plata.",
      "entidades_detectadas": [
        "Alfa",
        "Mar del Plata",
        "Walter Santiago"
      ]
    },
    {
      "frase": "Desde temprano, se especuló sobre su participación luego de que se confirmara su ingreso al predio.",
      "entidades_detectadas": []
    },
    {
      "frase": "Su relación con figuras del espacio libertario es conocida; se rumorea incluso una cercanía con la jueza de la Libertad Avanza.",
      "entidades_detectadas": []
    },
    {
      "frase": "Contactamos a Santiago para obtener su versión.",
      "entidades_detectadas": [
        "Santiago"
      ]
    },
    {
      "frase": "— Buenos días, Alfa.",
      "entidades_detectadas": [
        "Alfa",
        "Buenos días"
      ]
    },
    {
      "frase": "Gracias por atendernos.",
      "entidades_detectadas": []
    },
    {
      "frase": "Su presencia en el acto libertario sorprendió a muchos.",
      "entidades_detectadas": []
    },
    {
      "frase": "Se dice que usted está cerca de algunos dirigentes del espacio liderado por Javier Milei.",
      "entidades_detectadas": [
        "Javier Milei"
      ]
    },
    {
      "frase": "¿Es cierto?",
      "entidades_detectadas": []
    },
    {
      "frase": "— Mira, cuando salí de *Gran Hermano*, me ofrecieron ocupar cargos en listas políticas, pero me negué.",
      "entidades_detectadas": [
        "Mira",
        "Gran Hermano"
      ]
    },
    {
      "frase": "Sin embargo, con el tiempo, me di cuenta de que se necesitan cambios, aunque sean duros.",
      "entidades_detectadas": []
    },
    {
      "frase": "Siempre he sido antikirchnerista y he criticado las políticas que, en mi opinión, destruyeron al país.",
      "entidades_detectadas": []
    },
    {
      "frase": "— ¿Y su cercanía con Daniel Scioli?",
      "entidades_detectadas": [
        "Daniel Scioli",
        "¿"
      ]
    },
    {
      "frase": "— Soy amigo de Daniel hace más de 40 años.",
      "entidades_detectadas": [
        "Soy",
        "Daniel"
      ]
    },
    {
      "frase": "Últimamente hemos estado más cerca: compartimos fines de semana, salimos juntos…  Un día, publicamos una foto donde Daniel luce una remera con el logo de “Mi Ley”, y eso generó mucha repercusión.",
      "entidades_detectadas": [
        "Daniel"
      ]
    },
    {
      "frase": "Esa foto desencadenó lo que está pasando ahora.",
      "entidades_detectadas": []
    },
    {
      "frase": "Scioli me comentó que lo estaban contactando para consultarlo sobre posibles candidaturas.",
      "entidades_detectadas": []
    },
    {
      "frase": "— Una fuente cercana a La Libertad Avanza nos dijo que incluso lo incluyeron en alguna lista de personalidades a evaluar.",
      "entidades_detectadas": [
        "La Libertad Avanza"
      ]
    },
    {
      "frase": "¿Puede confirmarlo?",
      "entidades_detectadas": [
        "¿"
      ]
    },
    {
      "frase": "— Sí, es cierto.",
      "entidades_detectadas": []
    },
    {
      "frase": "Debido a mi amistad con Scioli, y a que paso mucho tiempo en Mar del Plata (donde estoy desde diciembre por mi participación en la obra “Felices los cuatro”, con Fernanda Vives),  he tenido varios encuentros con él.",
      "entidades_detectadas": [
        "Scioli",
        "Mar del Plata"
      ]
    },
    {
      "frase": "— Se rumorea que está evaluando la posibilidad de integrarse a alguna lista, ¿a qué nivel?",
      "entidades_detectadas": [
        "¿"
      ]
    },
    {
      "frase": "— Siempre fui enemigo de la política, pero ahora me interesa sumarme a un proyecto de cambio.",
      "entidades_detectadas": []
    },
    {
      "frase": "No necesito nada, soy feliz con lo que tengo, pero quiero ayudar a construir una Argentina fuerte.",
      "entidades_detectadas": [
        "Argentina"
      ]
    },
    {
      "frase": "No me interesa la política como un medio para enriquecerme.",
      "entidades_detectadas": []
    },
    {
      "frase": "— ¿Y qué piensa de las críticas que ha recibido?",
      "entidades_detectadas": [
        "¿"
      ]
    },
    {
      "frase": "— He recibido muchos mensajes, desde ayer a la mañana mi teléfono no para.",
      "entidades_detectadas": []
    },
    {
      "frase": "Quiero ayudar a generar un cambio profundo en el país.",
      "entidades_detectadas": [
        "Quiero"
      ]
    },
    {
      "frase": "— ¿Se imagina en algún cargo legislativo o ejecutivo?",
      "entidades_detectadas": [
        "¿"
      ]
    },
    {
      "frase": "— Estoy abierto a sumarme al proyecto “Mi Ley” y analizar en qué puedo contribuir.",
      "entidades_detectadas": [
        "Estoy"
      ]
    },
    {
      "frase": "Si veo que estoy capacitado y que puedo aportar, me sumaré.",
      "entidades_detectadas": []
    },
    {
      "frase": "— ¿Qué tal fue su encuentro con Karina Milei?",
      "entidades_detectadas": [
        "Karina Milei",
        "¿Qué"
      ]
    },
    {
      "frase": "— La he cruzado varias veces en televisión.",
      "entidades_detectadas": []
    },
    {
      "frase": "Ayer la vi mucho más relajada y tranquila.",
      "entidades_detectadas": [
        "Ayer"
      ]
    },
    {
      "frase": "Fue un encuentro muy agradable.",
      "entidades_detectadas": []
    },
    {
      "frase": "— Cuando alguien se mete en política, suele tener un proyecto en mente.",
      "entidades_detectadas": []
    },
    {
      "frase": "¿Cuál es el suyo?",
      "entidades_detectadas": [
        "¿Cuál"
      ]
    },
    {
      "frase": "— Me preocupa la inseguridad en la provincia de Buenos Aires, donde vive mi hija y mis nietas.",
      "entidades_detectadas": [
        "provincia de Buenos Aires"
      ]
    },
    {
      "frase": "Quiero ayudar a implementar políticas que mejoren la seguridad.",
      "entidades_detectadas": [
        "Quiero"
      ]
    },
    {
      "frase": "También me preocupa la educación; vi a un estudiante de segundo año de economía que no sabía sumar.",
      "entidades_detectadas": [
        "También"
      ]
    },
    {
      "frase": "— Alfa, ministro de Seguridad...",
      "entidades_detectadas": [
        "Alfa"
      ]
    },
    {
      "frase": "el Mago Sin Dientes, ministro de Educación...",
      "entidades_detectadas": [
        "Educación"
      ]
    },
    {
      "frase": "— (Risas) Con el Mago Sin Dientes somos amigos hace 20 años.",
      "entidades_detectadas": [
        "Mago Sin Dientes",
        "Risas"
      ]
    },
    {
      "frase": "— Alfa, lamentablemente debemos finalizar la entrevista.",
      "entidades_detectadas": [
        "Alfa"
      ]
    },
    {
      "frase": "Gracias por su tiempo.",
      "entidades_detectadas": []
    },
    {
      "frase": "— Gracias a ustedes.",
      "entidades_detectadas": []
    },
    {
      "frase": "**",
      "entidades_detectadas": []
    }
  ],
  "entidades_mencionadas": [
    "Soy",
    "También",
    "Mar del Plata",
    "Daniel",
    "Gran Hermano",
    "Daniel Scioli",
    "Estoy",
    "Alfa",
    "¿Qué",
    "Walter Santiago",
    "Javier Milei",
    "Karina Milei",
    "Buenos días",
    "Contactamos",
    "¿Cuál",
    "Argentina",
    "repercusión",
    "Ayer",
    "Scioli",
    "Quiero",
    "Santiago",
    "Educación",
    "provincia de Buenos Aires",
    "Mago Sin Dientes",
    "¿",
    "Me",
    "Mira"
  ]
}